rtgo/ReadyThready.py
rtgo/__init__.py
rtgo/_mythreads.py
rtgo-0.0.7.dist-info/LICENCE.txt
rtgo-0.0.7.dist-info/METADATA
rtgo-0.0.7.dist-info/WHEEL
rtgo-0.0.7.dist-info/top_level.txt
rtgo-0.0.7.dist-info/RECORD
